[
	{ "s": "ФАЙЛ", "p": [21, 11, 19, 14, 5, 25, 16, 15, 13, 6] },
	{ "s": "ФАЙЛА", "p": [19, 14, 13, 22, 16, 24, 21, 15, 7] },
	{ "s": "ФАЙЛАМИ", "p": [14, 18, 21, 7] },
	{ "s": "ФАЙЛАХ", "p": [21] },
	{ "s": "ФАЙЛЕ", "p": [23, 14, 11] },
	{ "s": "ФАЙЛОВ", "p": [19, 18, 14, 15, 26, 21, 20, 7] },
	{ "s": "ФАЙЛОВОГО", "p": [19, 18] },
	{ "s": "ФАЙЛОВОЙ", "p": [18, 21] },
	{ "s": "ФАЙЛОВОМ", "p": [19] },
	{ "s": "ФАЙЛОВУЮ", "p": [19, 18] },
	{ "s": "ФАЙЛОВЫЕ", "p": [19] },
	{ "s": "ФАЙЛОВЫМИ", "p": [18, 2, 26] },
	{ "s": "ФАЙЛОВЫХ", "p": [9, 25, 23, 14, 8] },
	{ "s": "ФАЙЛОМ", "p": [19] },
	{ "s": "ФАЙЛУ", "p": [21] },
	{ "s": "ФАЙЛЫ", "p": [18, 19, 21, 15, 25] },
	{ "s": "ФИГУРНЫХ", "p": [8] },
	{ "s": "ФИКСАЦИИ", "p": [17] },
	{ "s": "ФИКСИРОВАТЬ", "p": [19, 17] },
	{ "s": "ФИЛЬТР", "p": [18] },
	{ "s": "ФИЛЬТРАЦИИ", "p": [13] },
	{ "s": "ФИЛЬТРАЦИЯ", "p": [17, 9] },
	{ "s": "ФИЛЬТРУ", "p": [18] },
	{ "s": "ФИНИШ", "p": [22] },
	{ "s": "ФИНИШУ", "p": [22] },
	{ "s": "ФЛАГА", "p": [23] },
	{ "s": "ФЛАГОМ", "p": [8] },
	{ "s": "ФОРМАТ", "p": [14] },
	{ "s": "ФОРМАТАМИ", "p": [2] },
	{ "s": "ФОРМАТАХ", "p": [21, 2] },
	{ "s": "ФОРМАТЫ", "p": [14] },
	{ "s": "ФРЕЙМВОРК", "p": [26, 2] },
	{ "s": "ФУНКЦИИ", "p": [24, 8, 5] },
	{ "s": "ФУНКЦИЙ", "p": [14] },
	{ "s": "ФУНКЦИОНАЛ", "p": [25, 18, 15] },
	{ "s": "ФУНКЦИОНАЛОМ", "p": [26] },
	{ "s": "ФУНКЦИОНАЛЬНОСТЬ", "p": [25] },
	{ "s": "ФУНКЦИОНАЛЬНОСТЬЮ", "p": [23, 20] },
	{ "s": "ФУНКЦИЯ", "p": [10] }
]